{
  "author": "moyongfeng",
  "time": "Thu Jan  8 15:19:04 2015",
  "ratio": 1.7778,
  "backgroundColor": "#C7B51E",
  "heroColorIndex": 16,
  "normalBlockColor": "#FFFFFF",
  "deathBlockColor": "#000000",
  "deathCircleColor": "#000000",
  "buttonColor": "#FEE132",
  "pushableBlockColor": "#DC96A8",
  "spawnPosition": "44.3398,393.348",
  "lightPosition": "568.422,522.387",
  "lightMoving": true,
  "shadowDarkness": 0.098,
  "useSoftShadow": false,
  "gradientCenter": "451.312,511.832",
  "gradientColorSrc": "#22C4DE",
  "gradientColorDst": "#326F9D",
  "paletteFile": "palette/color01.json",
  "fx": [ 
  ],
  "stars": [ 
  ],
  "blocks": [ 
    { 
      "id": 1,
      "size": "960,10",
      "position": "480,5",
      "pickable": false,
      "rotatespeed": 0,
      "shadowLength": 100,
      "shadowEnable": true,
      "paletteIndex": -1,
      "flipUV": false,
      "textureName": "images/saw3.png",
      "initEvents": [],
      "kind": "BLOCK"
    },
    { 
      "id": 2,
      "size": "960,10",
      "position": "480,534.993",
      "pickable": false,
      "rotatespeed": 0,
      "shadowLength": 100,
      "shadowEnable": true,
      "paletteIndex": -1,
      "flipUV": false,
      "textureName": "images/saw3.png",
      "initEvents": [],
      "kind": "BLOCK"
    },
    { 
      "id": 3,
      "size": "10,539.993",
      "position": "5,269.997",
      "pickable": false,
      "rotatespeed": 0,
      "shadowLength": 100,
      "shadowEnable": true,
      "paletteIndex": -1,
      "flipUV": false,
      "textureName": "images/saw3.png",
      "initEvents": [],
      "kind": "BLOCK"
    },
    { 
      "id": 4,
      "size": "10,539.993",
      "position": "955,269.997",
      "pickable": false,
      "rotatespeed": 0,
      "shadowLength": 100,
      "shadowEnable": true,
      "paletteIndex": -1,
      "flipUV": false,
      "textureName": "images/saw3.png",
      "initEvents": [],
      "kind": "BLOCK"
    },
    { 
      "id": 5,
      "size": "100,15",
      "position": "59.4766,366.117",
      "pickable": true,
      "rotatespeed": 0,
      "shadowLength": 100,
      "shadowEnable": true,
      "paletteIndex": 17,
      "flipUV": false,
      "textureName": "images/saw3.png",
      "initEvents": [],
      "kind": "BLOCK"
    },
    { 
      "id": 6,
      "size": "100,15",
      "position": "260.516,366.117",
      "pickable": true,
      "rotatespeed": 0,
      "shadowLength": 100,
      "shadowEnable": true,
      "paletteIndex": 17,
      "flipUV": false,
      "textureName": "images/saw3.png",
      "initEvents": [],
      "kind": "BLOCK"
    },
    { 
      "id": 7,
      "size": "100,15",
      "position": "478.355,366.117",
      "pickable": true,
      "rotatespeed": 0,
      "shadowLength": 100,
      "shadowEnable": true,
      "paletteIndex": 17,
      "flipUV": false,
      "textureName": "images/saw3.png",
      "initEvents": [],
      "kind": "BLOCK"
    },
    { 
      "id": 8,
      "size": "100,15",
      "position": "689.355,366.117",
      "pickable": true,
      "rotatespeed": 0,
      "shadowLength": 100,
      "shadowEnable": true,
      "paletteIndex": 17,
      "flipUV": false,
      "textureName": "images/saw3.png",
      "initEvents": [],
      "kind": "BLOCK"
    },
    { 
      "id": 9,
      "size": "100,15",
      "position": "900.598,366.117",
      "pickable": true,
      "rotatespeed": 0,
      "shadowLength": 100,
      "shadowEnable": true,
      "paletteIndex": 17,
      "flipUV": false,
      "textureName": "images/saw3.png",
      "initEvents": [],
      "kind": "BLOCK"
    },
    { 
      "id": 10,
      "size": "157,15",
      "position": "88.3867,210.289",
      "pickable": true,
      "rotatespeed": 0,
      "shadowLength": 100,
      "shadowEnable": true,
      "paletteIndex": 17,
      "flipUV": false,
      "textureName": "images/saw3.png",
      "initEvents": [],
      "kind": "BLOCK"
    },
    { 
      "id": 11,
      "size": "200,15",
      "position": "850.387,210.289",
      "pickable": true,
      "rotatespeed": 0,
      "shadowLength": 100,
      "shadowEnable": true,
      "paletteIndex": 17,
      "flipUV": false,
      "textureName": "images/saw3.png",
      "initEvents": [],
      "kind": "BLOCK"
    },
    { 
      "id": 12,
      "size": "620,15",
      "position": "476.57,102.492",
      "pickable": true,
      "rotatespeed": 0,
      "shadowLength": 100,
      "shadowEnable": true,
      "paletteIndex": 17,
      "flipUV": false,
      "textureName": "images/saw3.png",
      "initEvents": [],
      "kind": "BLOCK"
    },
    { 
      "id": 13,
      "size": "15,100",
      "position": "794.02,59.9922",
      "pickable": true,
      "rotatespeed": 0,
      "shadowLength": 100,
      "shadowEnable": true,
      "paletteIndex": 17,
      "flipUV": false,
      "textureName": "images/saw3.png",
      "initEvents": [],
      "kind": "BLOCK"
    },
    { 
      "id": 14,
      "size": "15,195",
      "position": "159.523,107.367",
      "pickable": true,
      "rotatespeed": 0,
      "shadowLength": 100,
      "shadowEnable": true,
      "paletteIndex": 17,
      "flipUV": false,
      "textureName": "images/saw3.png",
      "initEvents": [],
      "kind": "BLOCK"
    },
    { 
      "id": 15,
      "size": "15,100",
      "position": "763.914,159.582",
      "pickable": true,
      "rotatespeed": 0,
      "shadowLength": 100,
      "shadowEnable": true,
      "paletteIndex": 17,
      "flipUV": false,
      "textureName": "images/saw3.png",
      "initEvents": [],
      "kind": "BLOCK"
    },
    { 
      "id": 16,
      "size": "25,25",
      "position": "897.109,441.785",
      "pickable": true,
      "rotatespeed": 0,
      "shadowLength": 100,
      "shadowEnable": false,
      "paletteIndex": 10,
      "flipUV": false,
      "textureName": "images/rect.png",
      "triggerEvents": ["open_door 15", "hide 16"],
      "initEvents": ["show 16"],
      "kind": "DEATH"
    },
    { 
      "id": 17,
      "size": "30,35",
      "position": "899.383,27.1211",
      "pickable": true,
      "rotatespeed": 0,
      "shadowLength": 100,
      "shadowEnable": false,
      "paletteIndex": 5,
      "flipUV": false,
      "textureName": "images/rect.png",
      "triggerEvents": ["exit"],
      "initEvents": ["hide 6", "hide 7", "hide 8"],
      "kind": "DEATH"
    },
    { 
      "id": 18,
      "size": "85,85",
      "position": "223.625,103.016",
      "pickable": true,
      "rotatespeed": 50,
      "shadowLength": 100,
      "shadowEnable": false,
      "paletteIndex": -1,
      "flipUV": false,
      "textureName": "images/saw3.png",
      "triggerEvents": ["die"],
      "initEvents": [],
      "pathSpeed": 490,
      "pingpong": true,
      "pause": false,
      "pathWaitTime": -1,
      "pathes": [ 
        { 
          "position": "223.625,103.016",
          "width": 1,
          "height": 1,
          "waittime": 1
        },
        { 
          "position": "713.625,103.016",
          "width": 1,
          "height": 1,
          "waittime": 1
        }
      ],
      "kind": "DEATH_CIRCLE"
    },
    { 
      "id": 19,
      "size": "60,60",
      "position": "130.418,211.074",
      "pickable": true,
      "rotatespeed": 50,
      "shadowLength": 100,
      "shadowEnable": false,
      "paletteIndex": -1,
      "flipUV": false,
      "textureName": "images/saw3.png",
      "triggerEvents": ["die"],
      "initEvents": [],
      "pathSpeed": 90,
      "pingpong": true,
      "pause": false,
      "pathWaitTime": -1,
      "pathes": [ 
        { 
          "position": "130.418,211.074",
          "width": 1,
          "height": 1,
          "waittime": 1
        },
        { 
          "position": "40.418,211.074",
          "width": 1,
          "height": 1,
          "waittime": 1
        }
      ],
      "kind": "DEATH_CIRCLE"
    },
    { 
      "id": 20,
      "size": "60,60",
      "position": "807.75,208.527",
      "pickable": true,
      "rotatespeed": 50,
      "shadowLength": 100,
      "shadowEnable": false,
      "paletteIndex": -1,
      "flipUV": false,
      "textureName": "images/saw3.png",
      "triggerEvents": ["die"],
      "initEvents": [],
      "pathSpeed": 110,
      "pingpong": true,
      "pause": false,
      "pathWaitTime": -1,
      "pathes": [ 
        { 
          "position": "807.75,208.527",
          "width": 1,
          "height": 1,
          "waittime": 1
        },
        { 
          "position": "917.75,208.527",
          "width": 1,
          "height": 1,
          "waittime": 1
        }
      ],
      "kind": "DEATH_CIRCLE"
    }
  ],
  "timeEvents": [
    {
      "initDelay": 1,
      "loop": 1,
      "events": [
        { "event": ["show 6", "hide 7", "show 8"], "delay": 1.5},
        { "event": ["hide 6", "show 7", "hide 8"], "delay": 1.5}
      ]
    }
  ]
}